setup.py
chroniker/__init__.py
chroniker/timer.py
chroniker.egg-info/PKG-INFO
chroniker.egg-info/SOURCES.txt
chroniker.egg-info/dependency_links.txt
chroniker.egg-info/top_level.txt
chroniker.egg-info/zip-safe