Metadata-Version: 1.0
Name: chroniker
Version: 0.0.0
Summary: Profiling and timing tools for Python.
Home-page: http://github.com/wnyc/to_sentry
Author: Adam DePrince
Author-email: adeprince@nypublicradio.org
License: BSD
Platform: UNKNOWN
Classifier: Intended Audience :: Developers
Classifier: Intended Audience :: System Administrators
Classifier: Operating System :: OS Independent
Classifier: Topic :: Software Development
